{"v":"5.7.3","fr":60,"ip":0,"op":240,"w":705,"h":536,"nm":"Sit Back","ddd":0,"assets":[{"id":"comp_0","layers":[{"ddd":0,"ind":1,"ty":4,"nm":"Layer 2 Outlines","parent":2,"sr":1,"ks":{"o":{"a":0,"k":100,"ix":11},"r":{"a":1,"k":[{"i":{"x":[0.667],"y":[1]},"o":{"x":[0.333],"y":[0]},"t":0,"s":[0]},{"i":{"x":[0.667],"y":[1]},"o":{"x":[0.333],"y":[0]},"t":60,"s":[-11]},{"i":{"x":[0.667],"y":[1]},"o":{"x":[0.333],"y":[0]},"t":120,"s":[0]},{"i":{"x":[0.667],"y":[1]},"o":{"x":[0.333],"y":[0]},"t":180,"s":[-11]},{"t":239,"s":[0]}],"ix":10},"p":{"a":0,"k":[404.969,94.67,0],"ix":2},"a":{"a":0,"k":[404.969,94.67,0],"ix":1},"s":{"a":0,"k":[100,100,100],"ix":6}},"ao":0,"shapes":[{"ty":"gr","it":[{"ind":0,"ty":"sh","ix":1,"ks":{"a":0,"k":{"i":[[-10.48,-17.451],[-16.915,-20.809],[5.297,0],[0,0],[6.8,-0.817],[0,0],[4.685,0]],"o":[[0,0],[-2.688,-24.523],[-5.297,0],[0,0],[-6.8,0.817],[0,0],[-4.684,0]],"v":[[-11.963,6.634],[22.443,23.697],[5.04,-17.57],[3.011,-8.177],[-8.976,-22.879],[-7.199,-5.094],[-16.809,-17.57]],"c":true},"ix":2},"nm":"Path 1","mn":"ADBE Vector Shape - Group","hd":false},{"ty":"fl","c":{"a":0,"k":[0,0,0,1],"ix":4},"o":{"a":0,"k":100,"ix":5},"r":1,"bm":0,"nm":"Fill 1","mn":"ADBE Vector Graphic - Fill","hd":false},{"ty":"tr","p":{"a":0,"k":[423.153,38.36],"ix":2},"a":{"a":0,"k":[0,0],"ix":1},"s":{"a":0,"k":[100,100],"ix":3},"r":{"a":0,"k":0,"ix":6},"o":{"a":0,"k":100,"ix":7},"sk":{"a":0,"k":0,"ix":4},"sa":{"a":0,"k":0,"ix":5},"nm":"Transform"}],"nm":"Group 1","np":4,"cix":2,"bm":0,"ix":1,"mn":"ADBE Vector Group","hd":false},{"ty":"gr","it":[{"ind":0,"ty":"sh","ix":1,"ks":{"a":0,"k":{"i":[[0.391,0],[0.175,-0.44],[2.615,-2.174],[0.705,-0.44],[0.66,-2.214],[-0.286,-0.291],[-2.409,-0.103],[-0.112,0],[-1.329,1.176],[0.173,0.457],[0.472,0],[0.212,-0.187],[2.384,0.593],[0.418,0.392],[-0.816,0.53],[0,0],[-1.784,4.442],[0.214,0.315]],"o":[[-0.47,0],[-1.257,3.13],[-0.562,0.466],[-1.695,1.058],[-0.124,0.422],[1.619,1.652],[0.113,0.005],[2.812,0],[0.365,-0.324],[-0.172,-0.457],[-0.272,0],[-2.165,1.916],[-0.585,-0.146],[0.356,-0.806],[0,0],[4.72,-3.064],[0.144,-0.361],[-0.215,-0.32]],"v":[[5.999,-9.168],[4.936,-8.444],[-0.901,-0.452],[-2.834,0.87],[-7.11,5.341],[-6.855,6.479],[-0.697,9.161],[-0.361,9.168],[5.873,6.428],[6.19,5.144],[5.112,4.38],[4.362,4.67],[-2.298,6.604],[-4.714,5.463],[-2.54,3.477],[-2.444,3.415],[7.09,-7.587],[6.982,-8.65]],"c":true},"ix":2},"nm":"Path 1","mn":"ADBE Vector Shape - Group","hd":false},{"ty":"fl","c":{"a":0,"k":[0.136999990426,0.122000002394,0.125,1],"ix":4},"o":{"a":0,"k":100,"ix":5},"r":1,"bm":0,"nm":"Fill 1","mn":"ADBE Vector Graphic - Fill","hd":false},{"ty":"tr","p":{"a":0,"k":[412.64,71.301],"ix":2},"a":{"a":0,"k":[0,0],"ix":1},"s":{"a":0,"k":[100,100],"ix":3},"r":{"a":0,"k":0,"ix":6},"o":{"a":0,"k":100,"ix":7},"sk":{"a":0,"k":0,"ix":4},"sa":{"a":0,"k":0,"ix":5},"nm":"Transform"}],"nm":"Group 2","np":4,"cix":2,"bm":0,"ix":2,"mn":"ADBE Vector Group","hd":false},{"ty":"gr","it":[{"ind":0,"ty":"sh","ix":1,"ks":{"a":0,"k":{"i":[[0.207,0.376],[0.425,0],[0.21,-0.332],[1.524,-1.271],[1.318,0],[0.439,0.266],[-0.938,1.695],[-1.62,1.203],[0.156,0.471],[0.496,0],[0.203,-0.151],[1.166,-2.482],[-1.146,-0.906],[-1.115,0],[-0.989,0.611],[-1.942,3.077]],"o":[[-0.21,-0.382],[-0.382,0],[-1.086,1.721],[-0.931,0.775],[-0.476,0],[-1.389,-0.838],[0.849,-1.537],[0.402,-0.299],[-0.158,-0.48],[-0.246,0],[-2.159,1.603],[-1.946,4.139],[0.862,0.684],[1.064,0],[1.623,-1.003],[0.23,-0.366]],"v":[[7.336,-1.127],[6.306,-1.746],[5.361,-1.216],[1.173,3.09],[-2.464,4.895],[-3.824,4.501],[-2.91,-1.002],[0.81,-5.131],[1.215,-6.398],[0.103,-7.214],[-0.586,-6.983],[-5.596,-0.827],[-5.44,6.168],[-2.419,7.214],[0.719,6.279],[7.298,0.059]],"c":true},"ix":2},"nm":"Path 1","mn":"ADBE Vector Shape - Group","hd":false},{"ty":"fl","c":{"a":0,"k":[0.136999990426,0.122000002394,0.125,1],"ix":4},"o":{"a":0,"k":100,"ix":5},"r":1,"bm":0,"nm":"Fill 1","mn":"ADBE Vector Graphic - Fill","hd":false},{"ty":"tr","p":{"a":0,"k":[427.81,67.113],"ix":2},"a":{"a":0,"k":[0,0],"ix":1},"s":{"a":0,"k":[100,100],"ix":3},"r":{"a":0,"k":0,"ix":6},"o":{"a":0,"k":100,"ix":7},"sk":{"a":0,"k":0,"ix":4},"sa":{"a":0,"k":0,"ix":5},"nm":"Transform"}],"nm":"Group 3","np":4,"cix":2,"bm":0,"ix":3,"mn":"ADBE Vector Group","hd":false},{"ty":"gr","it":[{"ind":0,"ty":"sh","ix":1,"ks":{"a":0,"k":{"i":[[-3.251,-1.385],[-0.534,0],[-0.872,0.851],[-1.187,1.927],[-0.4,0.61],[0.205,0.38],[0.423,0],[0.211,-0.323],[0.339,-0.523],[0.826,-1.197],[1.855,-0.306],[0.282,0.337],[-0.124,0.689],[-0.454,1.154],[-1.538,1.614],[0.175,0.408],[0.476,0],[0.225,-0.236],[0.902,-2.729]],"o":[[0.485,0.207],[1.968,0],[1.627,-1.589],[0.394,-0.641],[0.239,-0.364],[-0.206,-0.381],[-0.376,0],[-0.342,0.521],[-0.782,1.205],[-0.976,1.414],[-0.568,0.094],[-0.318,-0.382],[0.156,-0.865],[0.704,-1.793],[0.315,-0.33],[-0.183,-0.428],[-0.323,0],[-1.96,2.054],[-0.55,1.666]],"v":[[-4.182,6.89],[-2.646,7.202],[1.949,4.925],[5.99,-0.583],[7.174,-2.468],[7.228,-3.657],[6.193,-4.283],[5.255,-3.768],[4.236,-2.201],[1.818,1.447],[-2.372,4.83],[-3.652,4.469],[-3.963,2.761],[-3.081,-0.158],[0.298,-5.292],[0.525,-6.489],[-0.576,-7.202],[-1.426,-6.837],[-5.738,0.372]],"c":true},"ix":2},"nm":"Path 1","mn":"ADBE Vector Shape - Group","hd":false},{"ty":"fl","c":{"a":0,"k":[0.136999990426,0.122000002394,0.125,1],"ix":4},"o":{"a":0,"k":100,"ix":5},"r":1,"bm":0,"nm":"Fill 1","mn":"ADBE Vector Graphic - Fill","hd":false},{"ty":"tr","p":{"a":0,"k":[412.333,59.213],"ix":2},"a":{"a":0,"k":[0,0],"ix":1},"s":{"a":0,"k":[100,100],"ix":3},"r":{"a":0,"k":0,"ix":6},"o":{"a":0,"k":100,"ix":7},"sk":{"a":0,"k":0,"ix":4},"sa":{"a":0,"k":0,"ix":5},"nm":"Transform"}],"nm":"Group 4","np":4,"cix":2,"bm":0,"ix":4,"mn":"ADBE Vector Group","hd":false},{"ty":"gr","it":[{"ind":0,"ty":"sh","ix":1,"ks":{"a":0,"k":{"i":[[14.817,-0.774],[-0.004,-0.004],[-53.529,-11.604],[-7.372,12.072],[1.133,10.136]],"o":[[0.004,0.004],[-23.518,27.181],[13.697,2.909],[4.494,-7.331],[-7.775,-11.295]],"v":[[10.11,-30.245],[10.122,-30.232],[7.601,27.598],[38.313,18.947],[44.795,-11.911]],"c":true},"ix":2},"nm":"Path 1","mn":"ADBE Vector Shape - Group","hd":false},{"ty":"fl","c":{"a":0,"k":[0.305999995213,0.642999985639,0.611999990426,1],"ix":4},"o":{"a":0,"k":100,"ix":5},"r":1,"bm":0,"nm":"Fill 1","mn":"ADBE Vector Graphic - Fill","hd":false},{"ty":"tr","p":{"a":0,"k":[400.802,73.968],"ix":2},"a":{"a":0,"k":[0,0],"ix":1},"s":{"a":0,"k":[100,100],"ix":3},"r":{"a":0,"k":0,"ix":6},"o":{"a":0,"k":100,"ix":7},"sk":{"a":0,"k":0,"ix":4},"sa":{"a":0,"k":0,"ix":5},"nm":"Transform"}],"nm":"Group 5","np":4,"cix":2,"bm":0,"ix":5,"mn":"ADBE Vector Group","hd":false}],"ip":0,"op":240,"st":0,"bm":0},{"ddd":0,"ind":2,"ty":4,"nm":"Illustration Main Sit Back Outlines","sr":1,"ks":{"o":{"a":0,"k":100,"ix":11},"r":{"a":0,"k":0,"ix":10},"p":{"a":1,"k":[{"i":{"x":0.667,"y":1},"o":{"x":0.333,"y":0},"t":0,"s":[278.469,211.67,0],"to":[0,0,0],"ti":[0,0,0]},{"i":{"x":0.667,"y":1},"o":{"x":0.333,"y":0},"t":121,"s":[278.469,246.67,0],"to":[0,0,0],"ti":[0,0,0]},{"t":239,"s":[278.469,211.67,0]}],"ix":2},"a":{"a":0,"k":[278.469,211.67,0],"ix":1},"s":{"a":0,"k":[100,100,100],"ix":6}},"ao":0,"shapes":[{"ty":"gr","it":[{"ind":0,"ty":"sh","ix":1,"ks":{"a":0,"k":{"i":[[-0.276,0.439],[0.192,-0.236],[-0.253,0.423]],"o":[[0.06,0.03],[-0.666,0.823],[0.224,-0.374]],"v":[[0.131,-0.802],[0.665,-0.271],[-0.604,0.379]],"c":true},"ix":2},"nm":"Path 1","mn":"ADBE Vector Shape - Group","hd":false},{"ty":"fl","c":{"a":0,"k":[1,1,1,1],"ix":4},"o":{"a":0,"k":100,"ix":5},"r":1,"bm":0,"nm":"Fill 1","mn":"ADBE Vector Graphic - Fill","hd":false},{"ty":"tr","p":{"a":0,"k":[244.141,225.577],"ix":2},"a":{"a":0,"k":[0,0],"ix":1},"s":{"a":0,"k":[100,100],"ix":3},"r":{"a":0,"k":0,"ix":6},"o":{"a":0,"k":100,"ix":7},"sk":{"a":0,"k":0,"ix":4},"sa":{"a":0,"k":0,"ix":5},"nm":"Transform"}],"nm":"Group 1","np":4,"cix":2,"bm":0,"ix":1,"mn":"ADBE Vector Group","hd":false},{"ty":"gr","it":[{"ind":0,"ty":"sh","ix":1,"ks":{"a":0,"k":{"i":[[-2.495,6.703],[-1.326,-0.634],[0.593,-0.385]],"o":[[1.316,0.57],[-0.543,0.607],[-4.993,3.238]],"v":[[-0.428,-3.352],[3.405,-1.402],[1.589,-0.149]],"c":true},"ix":2},"nm":"Path 1","mn":"ADBE Vector Shape - Group","hd":false},{"ty":"fl","c":{"a":0,"k":[1,1,1,1],"ix":4},"o":{"a":0,"k":100,"ix":5},"r":1,"bm":0,"nm":"Fill 1","mn":"ADBE Vector Graphic - Fill","hd":false},{"ty":"tr","p":{"a":0,"k":[241.138,235.518],"ix":2},"a":{"a":0,"k":[0,0],"ix":1},"s":{"a":0,"k":[100,100],"ix":3},"r":{"a":0,"k":0,"ix":6},"o":{"a":0,"k":100,"ix":7},"sk":{"a":0,"k":0,"ix":4},"sa":{"a":0,"k":0,"ix":5},"nm":"Transform"}],"nm":"Group 2","np":4,"cix":2,"bm":0,"ix":2,"mn":"ADBE Vector Group","hd":false},{"ty":"gr","it":[{"ind":0,"ty":"sh","ix":1,"ks":{"a":0,"k":{"i":[[1.802,-1.44],[0.494,0.384],[-1.306,1.72],[0.187,-0.172]],"o":[[-0.729,-0.021],[0.997,-1.959],[2.143,0.788],[-1.697,1.557]],"v":[[-1.971,3.125],[-3.645,2.389],[-0.198,-3.126],[3.458,-1.129]],"c":true},"ix":2},"nm":"Path 1","mn":"ADBE Vector Shape - Group","hd":false},{"ty":"fl","c":{"a":0,"k":[1,1,1,1],"ix":4},"o":{"a":0,"k":100,"ix":5},"r":1,"bm":0,"nm":"Fill 1","mn":"ADBE Vector Graphic - Fill","hd":false},{"ty":"tr","p":{"a":0,"k":[248.944,220.656],"ix":2},"a":{"a":0,"k":[0,0],"ix":1},"s":{"a":0,"k":[100,100],"ix":3},"r":{"a":0,"k":0,"ix":6},"o":{"a":0,"k":100,"ix":7},"sk":{"a":0,"k":0,"ix":4},"sa":{"a":0,"k":0,"ix":5},"nm":"Transform"}],"nm":"Group 3","np":4,"cix":2,"bm":0,"ix":3,"mn":"ADBE Vector Group","hd":false},{"ty":"gr","it":[{"ind":0,"ty":"sh","ix":1,"ks":{"a":0,"k":{"i":[[-0.194,-0.288],[0.929,0.258],[-6.16,3.827],[-0.231,-0.103]],"o":[[-0.907,0.327],[-0.901,-0.251],[0.198,-0.123],[4.727,2.112]],"v":[[5.976,-0.444],[-5.555,2.38],[0.949,-2.279],[1.729,-2.535]],"c":true},"ix":2},"nm":"Path 1","mn":"ADBE Vector Shape - Group","hd":false},{"ty":"fl","c":{"a":0,"k":[1,1,1,1],"ix":4},"o":{"a":0,"k":100,"ix":5},"r":1,"bm":0,"nm":"Fill 1","mn":"ADBE Vector Graphic - Fill","hd":false},{"ty":"tr","p":{"a":0,"k":[245.278,237.84],"ix":2},"a":{"a":0,"k":[0,0],"ix":1},"s":{"a":0,"k":[100,100],"ix":3},"r":{"a":0,"k":0,"ix":6},"o":{"a":0,"k":100,"ix":7},"sk":{"a":0,"k":0,"ix":4},"sa":{"a":0,"k":0,"ix":5},"nm":"Transform"}],"nm":"Group 4","np":4,"cix":2,"bm":0,"ix":4,"mn":"ADBE Vector Group","hd":false},{"ty":"gr","it":[{"ind":0,"ty":"sh","ix":1,"ks":{"a":0,"k":{"i":[[0.022,-0.015],[0.571,0.397],[-2.097,3.299],[-0.507,-0.143],[-0.588,-0.765]],"o":[[-0.935,-0.262],[-0.032,-0.513],[0.315,-0.495],[0.925,0.259],[-0.085,0.298]],"v":[[0.1,2.88],[-4.367,0.762],[-2.569,-2.262],[-1.308,-2.738],[4.666,-0.382]],"c":true},"ix":2},"nm":"Path 1","mn":"ADBE Vector Shape - Group","hd":false},{"ty":"fl","c":{"a":0,"k":[1,1,1,1],"ix":4},"o":{"a":0,"k":100,"ix":5},"r":1,"bm":0,"nm":"Fill 1","mn":"ADBE Vector Graphic - Fill","hd":false},{"ty":"tr","p":{"a":0,"k":[254.417,215.181],"ix":2},"a":{"a":0,"k":[0,0],"ix":1},"s":{"a":0,"k":[100,100],"ix":3},"r":{"a":0,"k":0,"ix":6},"o":{"a":0,"k":100,"ix":7},"sk":{"a":0,"k":0,"ix":4},"sa":{"a":0,"k":0,"ix":5},"nm":"Transform"}],"nm":"Group 5","np":4,"cix":2,"bm":0,"ix":5,"mn":"ADBE Vector Group","hd":false},{"ty":"gr","it":[{"ind":0,"ty":"sh","ix":1,"ks":{"a":0,"k":{"i":[[0.481,-0.271],[-0.318,0.234],[-0.587,-0.268],[-0.751,-0.52]],"o":[[-8.113,-3.264],[4.152,-3.061],[2.183,0.997],[-0.228,0.502]],"v":[[1.532,3.286],[-5.004,-0.166],[-0.38,-3.018],[6.581,0.105]],"c":true},"ix":2},"nm":"Path 1","mn":"ADBE Vector Shape - Group","hd":false},{"ty":"fl","c":{"a":0,"k":[1,1,1,1],"ix":4},"o":{"a":0,"k":100,"ix":5},"r":1,"bm":0,"nm":"Fill 1","mn":"ADBE Vector Graphic - Fill","hd":false},{"ty":"tr","p":{"a":0,"k":[262.054,218.909],"ix":2},"a":{"a":0,"k":[0,0],"ix":1},"s":{"a":0,"k":[100,100],"ix":3},"r":{"a":0,"k":0,"ix":6},"o":{"a":0,"k":100,"ix":7},"sk":{"a":0,"k":0,"ix":4},"sa":{"a":0,"k":0,"ix":5},"nm":"Transform"}],"nm":"Group 6","np":4,"cix":2,"bm":0,"ix":6,"mn":"ADBE Vector Group","hd":false},{"ty":"gr","it":[{"ind":0,"ty":"sh","ix":1,"ks":{"a":0,"k":{"i":[[0.603,0.517],[-2.759,2.14],[-6.122,-2.607],[6.846,-4.272],[3.036,1.557]],"o":[[1.591,-1.185],[0.653,-0.507],[-0.398,0.574],[-0.717,0.448],[-0.537,-0.275]],"v":[[-6.242,0.821],[-1.124,-3.053],[5.518,-0.809],[-0.604,3.111],[-4.577,1.917]],"c":true},"ix":2},"nm":"Path 1","mn":"ADBE Vector Shape - Group","hd":false},{"ty":"fl","c":{"a":0,"k":[1,1,1,1],"ix":4},"o":{"a":0,"k":100,"ix":5},"r":1,"bm":0,"nm":"Fill 1","mn":"ADBE Vector Graphic - Fill","hd":false},{"ty":"tr","p":{"a":0,"k":[247.867,229.484],"ix":2},"a":{"a":0,"k":[0,0],"ix":1},"s":{"a":0,"k":[100,100],"ix":3},"r":{"a":0,"k":0,"ix":6},"o":{"a":0,"k":100,"ix":7},"sk":{"a":0,"k":0,"ix":4},"sa":{"a":0,"k":0,"ix":5},"nm":"Transform"}],"nm":"Group 7","np":4,"cix":2,"bm":0,"ix":7,"mn":"ADBE Vector Group","hd":false},{"ty":"gr","it":[{"ind":0,"ty":"sh","ix":1,"ks":{"a":0,"k":{"i":[[-0.108,-0.216],[1.95,-1.238],[4.215,1.777],[-0.398,0.27]],"o":[[-1.902,1.271],[-2.32,-0.908],[0.157,-0.46],[7.372,3.342]],"v":[[5.718,-0.328],[-0.035,3.468],[-6.433,0.859],[-0.938,-3.468]],"c":true},"ix":2},"nm":"Path 1","mn":"ADBE Vector Shape - Group","hd":false},{"ty":"fl","c":{"a":0,"k":[1,1,1,1],"ix":4},"o":{"a":0,"k":100,"ix":5},"r":1,"bm":0,"nm":"Fill 1","mn":"ADBE Vector Graphic - Fill","hd":false},{"ty":"tr","p":{"a":0,"k":[255.638,223.928],"ix":2},"a":{"a":0,"k":[0,0],"ix":1},"s":{"a":0,"k":[100,100],"ix":3},"r":{"a":0,"k":0,"ix":6},"o":{"a":0,"k":100,"ix":7},"sk":{"a":0,"k":0,"ix":4},"sa":{"a":0,"k":0,"ix":5},"nm":"Transform"}],"nm":"Group 8","np":4,"cix":2,"bm":0,"ix":8,"mn":"ADBE Vector Group","hd":false},{"ty":"gr","it":[{"ind":0,"ty":"sh","ix":1,"ks":{"a":0,"k":{"i":[[-1.132,-0.598],[5.719,2.55],[-7.186,4.513],[-2.408,-0.977]],"o":[[-11.588,3.823],[-1.909,-0.851],[0.647,-0.407],[6.004,2.437]],"v":[[7.937,-0.095],[-6.123,1.226],[-1.111,-3.369],[2.293,-2.476]],"c":true},"ix":2},"nm":"Path 1","mn":"ADBE Vector Shape - Group","hd":false},{"ty":"fl","c":{"a":0,"k":[1,1,1,1],"ix":4},"o":{"a":0,"k":100,"ix":5},"r":1,"bm":0,"nm":"Fill 1","mn":"ADBE Vector Graphic - Fill","hd":false},{"ty":"tr","p":{"a":0,"k":[256.416,233.333],"ix":2},"a":{"a":0,"k":[0,0],"ix":1},"s":{"a":0,"k":[100,100],"ix":3},"r":{"a":0,"k":0,"ix":6},"o":{"a":0,"k":100,"ix":7},"sk":{"a":0,"k":0,"ix":4},"sa":{"a":0,"k":0,"ix":5},"nm":"Transform"}],"nm":"Group 9","np":4,"cix":2,"bm":0,"ix":9,"mn":"ADBE Vector Group","hd":false},{"ty":"gr","it":[{"ind":0,"ty":"sh","ix":1,"ks":{"a":0,"k":{"i":[[8.186,3.574],[-5.245,3.299],[4.774,-4.228]],"o":[[1.109,-0.83],[5.755,2.693],[-2.129,-0.565]],"v":[[-7.566,-0.785],[-2.544,-4.05],[3.015,4.051]],"c":true},"ix":2},"nm":"Path 1","mn":"ADBE Vector Shape - Group","hd":false},{"ty":"fl","c":{"a":0,"k":[1,1,1,1],"ix":4},"o":{"a":0,"k":100,"ix":5},"r":1,"bm":0,"nm":"Fill 1","mn":"ADBE Vector Graphic - Fill","hd":false},{"ty":"tr","p":{"a":0,"k":[273.398,224.039],"ix":2},"a":{"a":0,"k":[0,0],"ix":1},"s":{"a":0,"k":[100,100],"ix":3},"r":{"a":0,"k":0,"ix":6},"o":{"a":0,"k":100,"ix":7},"sk":{"a":0,"k":0,"ix":4},"sa":{"a":0,"k":0,"ix":5},"nm":"Transform"}],"nm":"Group 10","np":4,"cix":2,"bm":0,"ix":10,"mn":"ADBE Vector Group","hd":false},{"ty":"gr","it":[{"ind":0,"ty":"sh","ix":1,"ks":{"a":0,"k":{"i":[[-1.074,-0.53],[1.095,0.446],[0.243,0.495],[-0.025,0.014]],"o":[[-0.993,0.585],[-8.716,-3.547],[1.043,-0.876],[1.015,0.121]],"v":[[8.071,0.934],[0.645,3.486],[-8.04,-0.271],[-2.497,-3.932]],"c":true},"ix":2},"nm":"Path 1","mn":"ADBE Vector Shape - Group","hd":false},{"ty":"fl","c":{"a":0,"k":[1,1,1,1],"ix":4},"o":{"a":0,"k":100,"ix":5},"r":1,"bm":0,"nm":"Fill 1","mn":"ADBE Vector Graphic - Fill","hd":false},{"ty":"tr","p":{"a":0,"k":[266.128,228.5],"ix":2},"a":{"a":0,"k":[0,0],"ix":1},"s":{"a":0,"k":[100,100],"ix":3},"r":{"a":0,"k":0,"ix":6},"o":{"a":0,"k":100,"ix":7},"sk":{"a":0,"k":0,"ix":4},"sa":{"a":0,"k":0,"ix":5},"nm":"Transform"}],"nm":"Group 11","np":4,"cix":2,"bm":0,"ix":11,"mn":"ADBE Vector Group","hd":false},{"ty":"gr","it":[{"ind":0,"ty":"sh","ix":1,"ks":{"a":0,"k":{"i":[[0.148,-0.015],[-2.716,5.863],[-0.847,0.391],[12.192,-8.714]],"o":[[-1.937,-13.392],[0.366,-0.792],[1.451,-0.074],[-0.057,0.041]],"v":[[-5.28,11.185],[-4.075,-7.217],[-1.225,-11.116],[-4.975,11.149]],"c":true},"ix":2},"nm":"Path 1","mn":"ADBE Vector Shape - Group","hd":false},{"ty":"fl","c":{"a":0,"k":[1,1,1,1],"ix":4},"o":{"a":0,"k":100,"ix":5},"r":1,"bm":0,"nm":"Fill 1","mn":"ADBE Vector Graphic - Fill","hd":false},{"ty":"tr","p":{"a":0,"k":[221.137,195.204],"ix":2},"a":{"a":0,"k":[0,0],"ix":1},"s":{"a":0,"k":[100,100],"ix":3},"r":{"a":0,"k":0,"ix":6},"o":{"a":0,"k":100,"ix":7},"sk":{"a":0,"k":0,"ix":4},"sa":{"a":0,"k":0,"ix":5},"nm":"Transform"}],"nm":"Group 12","np":4,"cix":2,"bm":0,"ix":12,"mn":"ADBE Vector Group","hd":false},{"ty":"gr","it":[{"ind":0,"ty":"sh","ix":1,"ks":{"a":0,"k":{"i":[[-0.315,-2.502],[3.495,5.438],[-15.621,-1.963],[-2.116,-11.898]],"o":[[-1.293,-0.002],[-7.802,-12.137],[0.192,0.37],[0.812,4.565]],"v":[[5.024,17.126],[-5.874,9.728],[13.485,-15.163],[3.722,11.011]],"c":true},"ix":2},"nm":"Path 1","mn":"ADBE Vector Shape - Group","hd":false},{"ty":"fl","c":{"a":0,"k":[1,1,1,1],"ix":4},"o":{"a":0,"k":100,"ix":5},"r":1,"bm":0,"nm":"Fill 1","mn":"ADBE Vector Graphic - Fill","hd":false},{"ty":"tr","p":{"a":0,"k":[194.079,192.217],"ix":2},"a":{"a":0,"k":[0,0],"ix":1},"s":{"a":0,"k":[100,100],"ix":3},"r":{"a":0,"k":0,"ix":6},"o":{"a":0,"k":100,"ix":7},"sk":{"a":0,"k":0,"ix":4},"sa":{"a":0,"k":0,"ix":5},"nm":"Transform"}],"nm":"Group 13","np":4,"cix":2,"bm":0,"ix":13,"mn":"ADBE Vector Group","hd":false},{"ty":"gr","it":[{"ind":0,"ty":"sh","ix":1,"ks":{"a":0,"k":{"i":[[-0.408,-6.098],[4.333,0.728],[-3.778,7.721],[-3.105,2.884],[-0.02,-0.015],[0.434,-0.448],[0.465,-0.732]],"o":[[-3.1,1.905],[-2.668,-8.208],[1.432,-2.925],[4.25,0.549],[-0.178,0.54],[-1.698,1.749],[-4.103,6.464]],"v":[[5.336,13.521],[-7.242,15.771],[-5.868,-5.61],[1.391,-16.499],[9.91,-11.878],[8.893,-10.216],[6.306,-6.411]],"c":true},"ix":2},"nm":"Path 1","mn":"ADBE Vector Shape - Group","hd":false},{"ty":"fl","c":{"a":0,"k":[1,1,1,1],"ix":4},"o":{"a":0,"k":100,"ix":5},"r":1,"bm":0,"nm":"Fill 1","mn":"ADBE Vector Graphic - Fill","hd":false},{"ty":"tr","p":{"a":0,"k":[208.625,194.106],"ix":2},"a":{"a":0,"k":[0,0],"ix":1},"s":{"a":0,"k":[100,100],"ix":3},"r":{"a":0,"k":0,"ix":6},"o":{"a":0,"k":100,"ix":7},"sk":{"a":0,"k":0,"ix":4},"sa":{"a":0,"k":0,"ix":5},"nm":"Transform"}],"nm":"Group 14","np":4,"cix":2,"bm":0,"ix":14,"mn":"ADBE Vector Group","hd":false},{"ty":"gr","it":[{"ind":0,"ty":"sh","ix":1,"ks":{"a":0,"k":{"i":[[6.959,-1.249],[-0.552,1.33],[-0.187,0.785],[-0.196,0.888],[-0.981,1.502],[-1.103,0.602],[-23.565,-9.723],[-1.756,-5.677],[32.589,-12.518]],"o":[[1.424,-6.646],[0.351,-0.843],[0.098,-0.413],[0.027,-0.123],[0.693,-1.063],[2.224,0.913],[5.71,2.356],[1.266,4.091],[-5.873,2.256]],"v":[[-28.36,22.092],[-13.353,-12.238],[-11.623,-15.165],[-10.265,-17.596],[-8.452,-20.347],[-7.172,-21.916],[13.234,-12.369],[27.094,-3.37],[-10.428,17.451]],"c":true},"ix":2},"nm":"Path 1","mn":"ADBE Vector Shape - Group","hd":false},{"ty":"fl","c":{"a":0,"k":[0,0,0,1],"ix":4},"o":{"a":0,"k":100,"ix":5},"r":1,"bm":0,"nm":"Fill 1","mn":"ADBE Vector Graphic - Fill","hd":false},{"ty":"tr","p":{"a":0,"k":[262.014,228.734],"ix":2},"a":{"a":0,"k":[0,0],"ix":1},"s":{"a":0,"k":[100,100],"ix":3},"r":{"a":0,"k":0,"ix":6},"o":{"a":0,"k":100,"ix":7},"sk":{"a":0,"k":0,"ix":4},"sa":{"a":0,"k":0,"ix":5},"nm":"Transform"}],"nm":"Group 15","np":4,"cix":2,"bm":0,"ix":15,"mn":"ADBE Vector Group","hd":false},{"ty":"gr","it":[{"ind":0,"ty":"sh","ix":1,"ks":{"a":0,"k":{"i":[[0.463,-0.521],[-0.237,0.07]],"o":[[-0.255,-0.84],[0.281,-0.094]],"v":[[58.574,-22.752],[58.453,-23.817]],"c":true},"ix":2},"nm":"Path 1","mn":"ADBE Vector Shape - Group","hd":false},{"ind":1,"ty":"sh","ix":2,"ks":{"a":0,"k":{"i":[[-1.09,-0.3],[0.083,0.007],[0.177,0.458]],"o":[[-0.244,0.108],[-0.578,-0.045],[1.001,0.088]],"v":[[25.485,-41.242],[25.068,-41.065],[22.485,-41.932]],"c":true},"ix":2},"nm":"Path 2","mn":"ADBE Vector Shape - Group","hd":false},{"ind":2,"ty":"sh","ix":3,"ks":{"a":0,"k":{"i":[[-0.181,0.775],[-1.749,2.644],[-4.464,9.713],[-0.334,0.463],[6.891,5.671],[0.075,0.01],[12.794,3.813],[3.327,1.327],[2.018,0.348],[6.731,-0.47],[0.924,-2.984],[0.804,-2],[0.401,-0.97],[0.002,-0.004],[4.978,-20.564],[-47.856,-14.55],[-10.731,1.076]],"o":[[1.523,-6.124],[6.051,-9.236],[3.936,-8.596],[2.152,-8.146],[-0.756,-0.618],[-1.501,-0.183],[-1.721,-0.511],[-4.757,-1.908],[-5.391,-0.93],[-1.954,0.14],[-0.561,1.804],[-0.415,1.042],[-0.29,0.713],[-4.713,9.919],[-8.37,34.672],[22.757,6.928],[1.078,-0.11]],"v":[[29.743,55.061],[45.805,18.726],[53.286,1.485],[58.034,-11.439],[55.549,-31.312],[50.579,-34.37],[38.754,-38.937],[8.72,-47.568],[-6.96,-52.13],[-26.276,-56.349],[-30.964,-53.859],[-33.642,-49.109],[-34.969,-46.523],[-37.03,-41.883],[-47.915,-0.593],[-14.584,44.415],[26.835,55.767]],"c":true},"ix":2},"nm":"Path 3","mn":"ADBE Vector Shape - Group","hd":false},{"ty":"mm","mm":1,"nm":"Merge Paths 1","mn":"ADBE Vector Filter - Merge","hd":false},{"ty":"fl","c":{"a":0,"k":[0,0,0,1],"ix":4},"o":{"a":0,"k":100,"ix":5},"r":1,"bm":0,"nm":"Fill 1","mn":"ADBE Vector Graphic - Fill","hd":false},{"ty":"tr","p":{"a":0,"k":[202.779,195.578],"ix":2},"a":{"a":0,"k":[0,0],"ix":1},"s":{"a":0,"k":[100,100],"ix":3},"r":{"a":0,"k":0,"ix":6},"o":{"a":0,"k":100,"ix":7},"sk":{"a":0,"k":0,"ix":4},"sa":{"a":0,"k":0,"ix":5},"nm":"Transform"}],"nm":"Group 16","np":7,"cix":2,"bm":0,"ix":16,"mn":"ADBE Vector Group","hd":false},{"ty":"gr","it":[{"ind":0,"ty":"sh","ix":1,"ks":{"a":0,"k":{"i":[[0.523,-0.103],[0.366,0.183],[-0.439,0.88],[-23.137,1.957],[-10.841,-2.252],[0.199,-0.964],[0.968,0.205],[9.257,-0.783],[11.03,-22.137]],"o":[[-0.372,0.072],[-0.879,-0.438],[9.315,-18.695],[9.599,-0.815],[0.963,0.201],[-0.2,0.959],[-10.505,-2.184],[-15.222,1.293],[-0.257,0.513]],"v":[[-38.837,17.427],[-39.972,17.272],[-40.771,14.885],[8.823,-16.684],[39.629,-14.515],[41.011,-12.41],[38.906,-11.03],[9.123,-13.14],[-37.586,16.474]],"c":true},"ix":2},"nm":"Path 1","mn":"ADBE Vector Shape - Group","hd":false},{"ty":"fl","c":{"a":0,"k":[0,0,0,1],"ix":4},"o":{"a":0,"k":100,"ix":5},"r":1,"bm":0,"nm":"Fill 1","mn":"ADBE Vector Graphic - Fill","hd":false},{"ty":"tr","p":{"a":0,"k":[215.237,235.372],"ix":2},"a":{"a":0,"k":[0,0],"ix":1},"s":{"a":0,"k":[100,100],"ix":3},"r":{"a":0,"k":0,"ix":6},"o":{"a":0,"k":100,"ix":7},"sk":{"a":0,"k":0,"ix":4},"sa":{"a":0,"k":0,"ix":5},"nm":"Transform"}],"nm":"Group 17","np":4,"cix":2,"bm":0,"ix":17,"mn":"ADBE Vector Group","hd":false},{"ty":"gr","it":[{"ind":0,"ty":"sh","ix":1,"ks":{"a":0,"k":{"i":[[3.95,-2.324],[8.227,-12.13],[-7.26,1.691],[-41.272,-3.152],[0.14,-4.493],[-2.677,-2.702],[-5.72,0.897],[-1.956,9.139],[3.033,3.511],[7.671,4.573],[-3.409,7.451],[-6.487,-2.535],[-1.939,-22.829],[17.929,-3.093],[41.897,-42.154],[37.633,26.215],[5.09,4.365],[-5.654,5.546],[5.256,4.727],[2.114,8.872],[-5.452,8.701],[-18.798,3.266],[-16.119,-5.946],[-2.706,-1.907]],"o":[[-9.053,-0.879],[-12.3,18.138],[15.604,-3.638],[7.478,0.571],[-0.107,3.462],[4.363,4.406],[8.999,-1.412],[0.96,-4.488],[-6.036,-6.988],[-6.649,-3.964],[4.246,-9.279],[20.412,7.978],[2.46,28.965],[-59.303,10.235],[-54.459,54.797],[-5.768,-4.018],[-2.539,-2.176],[5.574,-5.469],[-6.637,-5.969],[-2.48,-10.406],[10.098,-16.115],[17.068,-2.966],[3.088,1.139],[3.783,2.666]],"v":[[12.351,-80.431],[-34.758,-79.487],[2.95,-56.388],[44.378,-47.577],[48.384,-27.602],[50.635,-16.443],[70.747,-12.315],[89.33,-27.758],[86.464,-40.039],[62.54,-53.492],[56.324,-70.549],[83.646,-71.159],[121.916,-23.948],[79.526,32.975],[6.062,60.579],[-75.321,88.387],[-121.837,53.013],[-66.445,-16.108],[-67.398,-28.398],[-82.758,-51.263],[-75.409,-81.193],[-29.42,-112.41],[23.299,-106.095],[32.264,-101.784]],"c":true},"ix":2},"nm":"Path 1","mn":"ADBE Vector Shape - Group","hd":false},{"ty":"fl","c":{"a":0,"k":[0,0,0,1],"ix":4},"o":{"a":0,"k":100,"ix":5},"r":1,"bm":0,"nm":"Fill 1","mn":"ADBE Vector Graphic - Fill","hd":false},{"ty":"tr","p":{"a":0,"k":[378.926,146.778],"ix":2},"a":{"a":0,"k":[0,0],"ix":1},"s":{"a":0,"k":[100,100],"ix":3},"r":{"a":0,"k":0,"ix":6},"o":{"a":0,"k":100,"ix":7},"sk":{"a":0,"k":0,"ix":4},"sa":{"a":0,"k":0,"ix":5},"nm":"Transform"}],"nm":"Group 18","np":4,"cix":2,"bm":0,"ix":18,"mn":"ADBE Vector Group","hd":false},{"ty":"gr","it":[{"ind":0,"ty":"sh","ix":1,"ks":{"a":0,"k":{"i":[[16.298,13.667],[1.981,-1.233],[23.8,-7.889],[7.25,-8.099],[7.697,-23.54],[-36.276,-7.832],[-1.104,-0.244],[4.815,-8.185],[-0.608,-0.265],[-10.159,-2.486],[-1.522,4.853],[-3.908,6.293],[-31.267,1.269],[-19.417,13.658]],"o":[[-3.025,-2.529],[-21.414,-11.41],[-10.097,3.362],[-50.771,-9.467],[-10.597,32.423],[1.077,0.249],[-5.437,7.847],[-0.376,0.636],[9.432,4.164],[6.217,1.519],[2.306,-7.233],[29.98,6.763],[24.267,-0.97],[-6.784,-19.855]],"v":[[54.243,-32.485],[47.499,-33.85],[-24.58,-42.006],[-50.225,-23.11],[-102.248,-21.533],[-81.356,11.6],[-78.013,12.351],[-93.387,36.424],[-92.626,38.04],[-63.253,48.376],[-52.432,40.344],[-43.647,20.224],[50.839,32.098],[117.632,11.865]],"c":true},"ix":2},"nm":"Path 1","mn":"ADBE Vector Shape - Group","hd":false},{"ty":"fl","c":{"a":0,"k":[0.305999995213,0.642999985639,0.611999990426,1],"ix":4},"o":{"a":0,"k":100,"ix":5},"r":1,"bm":0,"nm":"Fill 1","mn":"ADBE Vector Graphic - Fill","hd":false},{"ty":"tr","p":{"a":0,"k":[215.809,237.229],"ix":2},"a":{"a":0,"k":[0,0],"ix":1},"s":{"a":0,"k":[100,100],"ix":3},"r":{"a":0,"k":0,"ix":6},"o":{"a":0,"k":100,"ix":7},"sk":{"a":0,"k":0,"ix":4},"sa":{"a":0,"k":0,"ix":5},"nm":"Transform"}],"nm":"Group 19","np":4,"cix":2,"bm":0,"ix":19,"mn":"ADBE Vector Group","hd":false},{"ty":"gr","it":[{"ind":0,"ty":"sh","ix":1,"ks":{"a":0,"k":{"i":[[-0.077,14.34],[0.25,4.073],[7.504,-26.476],[27.418,-5.375]],"o":[[0.073,-13.722],[-2.975,-48.547],[-21.909,77.28],[-0.343,-1.748]],"v":[[-23.966,41.87],[-17.521,27.481],[16.539,-29.734],[-6.143,48.536]],"c":true},"ix":2},"nm":"Path 1","mn":"ADBE Vector Shape - Group","hd":false},{"ty":"fl","c":{"a":0,"k":[0,0,0,1],"ix":4},"o":{"a":0,"k":100,"ix":5},"r":1,"bm":0,"nm":"Fill 1","mn":"ADBE Vector Graphic - Fill","hd":false},{"ty":"tr","p":{"a":0,"k":[107.741,188.194],"ix":2},"a":{"a":0,"k":[0,0],"ix":1},"s":{"a":0,"k":[100,100],"ix":3},"r":{"a":0,"k":0,"ix":6},"o":{"a":0,"k":100,"ix":7},"sk":{"a":0,"k":0,"ix":4},"sa":{"a":0,"k":0,"ix":5},"nm":"Transform"}],"nm":"Group 20","np":4,"cix":2,"bm":0,"ix":20,"mn":"ADBE Vector Group","hd":false},{"ty":"gr","it":[{"ind":0,"ty":"sh","ix":1,"ks":{"a":0,"k":{"i":[[0.784,-0.73],[1.589,0.136],[1.605,0.045],[0.79,0.124],[0.546,1.336],[0.4,1.276],[0.577,1.779],[1.278,-0.442],[1.226,-0.521],[4.002,-0.64],[5.824,1.272],[2.777,2.276],[1.079,0.677],[0.367,1.275],[-1.974,0.526],[-1.847,0.234],[-8.71,3.543],[-2.055,1.247],[-2.305,-0.672],[-5.459,-2.182],[-0.799,-0.68],[-1.13,-1.141],[0.183,-2.327],[0.057,-2.409],[1.081,-2.771],[-0.262,-0.823]],"o":[[-1.59,-0.746],[-1.596,-0.138],[-0.802,-0.024],[-1.401,-0.221],[-0.504,-1.235],[-0.559,-1.786],[-0.448,-1.382],[-1.262,0.437],[-3.704,1.573],[-5.905,0.943],[-3.446,-0.751],[-1.017,-0.833],[-0.527,-1.364],[-0.604,-2.103],[1.801,-0.479],[9.343,-1.19],[2.259,-0.919],[1.824,-1.108],[5.657,1.65],[0.97,0.388],[1.221,1.036],[1.579,1.592],[-0.189,2.401],[-0.07,2.971],[-0.293,0.751],[-0.784,0.73]],"v":[[31.915,18.68],[27.199,18.824],[22.383,18.731],[19.986,18.528],[16.915,16.262],[15.647,12.458],[14.001,7.093],[10.891,5.425],[7.134,6.806],[-4.368,10.145],[-21.889,9.618],[-31.348,5.533],[-34.656,3.426],[-36.12,-0.429],[-33.441,-5.616],[-27.958,-6.734],[-0.971,-14.085],[5.342,-17.475],[11.482,-18.289],[28.119,-12.46],[30.815,-10.785],[34.273,-7.435],[36.542,-1.67],[36.23,5.552],[34.585,14.175],[34.266,16.488]],"c":true},"ix":2},"nm":"Path 1","mn":"ADBE Vector Shape - Group","hd":false},{"ty":"fl","c":{"a":0,"k":[0,0,0,1],"ix":4},"o":{"a":0,"k":100,"ix":5},"r":1,"bm":0,"nm":"Fill 1","mn":"ADBE Vector Graphic - Fill","hd":false},{"ty":"tr","p":{"a":0,"k":[122.644,287.641],"ix":2},"a":{"a":0,"k":[0,0],"ix":1},"s":{"a":0,"k":[100,100],"ix":3},"r":{"a":0,"k":0,"ix":6},"o":{"a":0,"k":100,"ix":7},"sk":{"a":0,"k":0,"ix":4},"sa":{"a":0,"k":0,"ix":5},"nm":"Transform"}],"nm":"Group 21","np":4,"cix":2,"bm":0,"ix":21,"mn":"ADBE Vector Group","hd":false},{"ty":"gr","it":[{"ind":0,"ty":"sh","ix":1,"ks":{"a":0,"k":{"i":[[0.377,-3.434],[9.68,19.285],[-15.548,-24.818]],"o":[[0,24.96],[-12.499,-24.903],[2.103,3.358]],"v":[[27.077,1.801],[-14.955,14.194],[24.369,-8.661]],"c":true},"ix":2},"nm":"Path 1","mn":"ADBE Vector Shape - Group","hd":false},{"ty":"fl","c":{"a":0,"k":[0.620000023935,0.620000023935,0.620000023935,1],"ix":4},"o":{"a":0,"k":100,"ix":5},"r":1,"bm":0,"nm":"Fill 1","mn":"ADBE Vector Graphic - Fill","hd":false},{"ty":"tr","p":{"a":0,"k":[73.558,195.945],"ix":2},"a":{"a":0,"k":[0,0],"ix":1},"s":{"a":0,"k":[100,100],"ix":3},"r":{"a":0,"k":0,"ix":6},"o":{"a":0,"k":100,"ix":7},"sk":{"a":0,"k":0,"ix":4},"sa":{"a":0,"k":0,"ix":5},"nm":"Transform"}],"nm":"Group 22","np":4,"cix":2,"bm":0,"ix":22,"mn":"ADBE Vector Group","hd":false},{"ty":"gr","it":[{"ind":0,"ty":"sh","ix":1,"ks":{"a":0,"k":{"i":[[41.692,-4.205],[2.546,13.78],[-15.808,-0.086]],"o":[[-11.704,0.181],[-1.737,-9.412],[28.316,0.154]],"v":[[-7.144,23.864],[-32.811,2.021],[-6.277,-23.96]],"c":true},"ix":2},"nm":"Path 1","mn":"ADBE Vector Shape - Group","hd":false},{"ty":"fl","c":{"a":0,"k":[0.620000023935,0.620000023935,0.620000023935,1],"ix":4},"o":{"a":0,"k":100,"ix":5},"r":1,"bm":0,"nm":"Fill 1","mn":"ADBE Vector Graphic - Fill","hd":false},{"ty":"tr","p":{"a":0,"k":[462.315,201.012],"ix":2},"a":{"a":0,"k":[0,0],"ix":1},"s":{"a":0,"k":[100,100],"ix":3},"r":{"a":0,"k":0,"ix":6},"o":{"a":0,"k":100,"ix":7},"sk":{"a":0,"k":0,"ix":4},"sa":{"a":0,"k":0,"ix":5},"nm":"Transform"}],"nm":"Group 23","np":4,"cix":2,"bm":0,"ix":23,"mn":"ADBE Vector Group","hd":false},{"ty":"gr","it":[{"ind":0,"ty":"sh","ix":1,"ks":{"a":0,"k":{"i":[[6.731,39.385],[21.132,0.1],[-4.319,26.342],[146.467,-36.783],[18.157,4.71],[20.112,-35.817],[-0.698,-8.143],[11.344,-12.773],[-5.988,-9.51],[-7.781,-2.826],[-21.869,6.327]],"o":[[-5.927,-34.516],[-2.17,-0.01],[4.961,-30.243],[-45.133,11.338],[-56.674,-14.702],[-27.603,49.157],[-15.744,-0.605],[-11.527,12.982],[13.712,21.774],[19.281,7.005],[5.007,-1.449]],"v":[[200.057,72.449],[138.995,52.574],[145.19,11.6],[46.564,-93.972],[-31.817,-93.168],[-156.352,-50.971],[-158.888,44.8],[-195.261,57.233],[-200.39,93.217],[-141.815,121.7],[83.383,124.428]],"c":true},"ix":2},"nm":"Path 1","mn":"ADBE Vector Shape - Group","hd":false},{"ty":"fl","c":{"a":0,"k":[0.620000023935,0.620000023935,0.620000023935,1],"ix":4},"o":{"a":0,"k":100,"ix":5},"r":1,"bm":0,"nm":"Fill 1","mn":"ADBE Vector Graphic - Fill","hd":false},{"ty":"tr","p":{"a":0,"k":[269.859,179.781],"ix":2},"a":{"a":0,"k":[0,0],"ix":1},"s":{"a":0,"k":[100,100],"ix":3},"r":{"a":0,"k":0,"ix":6},"o":{"a":0,"k":100,"ix":7},"sk":{"a":0,"k":0,"ix":4},"sa":{"a":0,"k":0,"ix":5},"nm":"Transform"}],"nm":"Group 24","np":4,"cix":2,"bm":0,"ix":24,"mn":"ADBE Vector Group","hd":false},{"ty":"gr","it":[{"ind":0,"ty":"sh","ix":1,"ks":{"a":0,"k":{"i":[[0.892,0.115],[-1.691,5.092],[1.688,4.356],[-4.469,1.069],[-0.367,-11.782],[-0.068,-2.175],[2.189,-4.036]],"o":[[-5.752,0],[5.895,-17.756],[-0.981,-2.533],[7.656,-1.831],[0.065,2.126],[0.14,4.481],[-1.786,3.292]],"v":[[-9.493,27.392],[-16.767,21.653],[-14.467,-19.35],[3.594,-27.287],[17.215,3.488],[16.413,9.837],[13.526,22.849]],"c":true},"ix":2},"nm":"Path 1","mn":"ADBE Vector Shape - Group","hd":false},{"ty":"fl","c":{"a":0,"k":[0.795999983245,0.905999995213,0.898000021542,1],"ix":4},"o":{"a":0,"k":100,"ix":5},"r":1,"bm":0,"nm":"Fill 1","mn":"ADBE Vector Graphic - Fill","hd":false},{"ty":"tr","p":{"a":0,"k":[414.178,315.636],"ix":2},"a":{"a":0,"k":[0,0],"ix":1},"s":{"a":0,"k":[100,100],"ix":3},"r":{"a":0,"k":0,"ix":6},"o":{"a":0,"k":100,"ix":7},"sk":{"a":0,"k":0,"ix":4},"sa":{"a":0,"k":0,"ix":5},"nm":"Transform"}],"nm":"Group 25","np":4,"cix":2,"bm":0,"ix":25,"mn":"ADBE Vector Group","hd":false},{"ty":"gr","it":[{"ind":0,"ty":"sh","ix":1,"ks":{"a":0,"k":{"i":[[0,0],[1.589,4.004],[-12.366,12.877],[-9.983,-1.745],[0.874,-1.663],[3.843,-7.285],[0.408,-1.086]],"o":[[-2.548,-2.477],[-5.204,-13.111],[3.685,-3.838],[4.946,0.865],[-9.526,18.138],[-0.499,0.948],[0,0]],"v":[[-3.382,26.435],[-16.287,22.586],[-6.222,-25.238],[16.27,-20.868],[16.507,-12.293],[5.296,24.216],[3.063,26.435]],"c":true},"ix":2},"nm":"Path 1","mn":"ADBE Vector Shape - Group","hd":false},{"ty":"fl","c":{"a":0,"k":[0.795999983245,0.905999995213,0.898000021542,1],"ix":4},"o":{"a":0,"k":100,"ix":5},"r":1,"bm":0,"nm":"Fill 1","mn":"ADBE Vector Graphic - Fill","hd":false},{"ty":"tr","p":{"a":0,"k":[114.145,319.391],"ix":2},"a":{"a":0,"k":[0,0],"ix":1},"s":{"a":0,"k":[100,100],"ix":3},"r":{"a":0,"k":0,"ix":6},"o":{"a":0,"k":100,"ix":7},"sk":{"a":0,"k":0,"ix":4},"sa":{"a":0,"k":0,"ix":5},"nm":"Transform"}],"nm":"Group 26","np":4,"cix":2,"bm":0,"ix":26,"mn":"ADBE Vector Group","hd":false}],"ip":0,"op":240,"st":0,"bm":0}]}],"layers":[{"ddd":0,"ind":1,"ty":0,"nm":"Sit Back main","refId":"comp_0","sr":1,"ks":{"o":{"a":0,"k":100,"ix":11},"r":{"a":0,"k":0,"ix":10},"p":{"a":0,"k":[352.5,268,0],"ix":2},"a":{"a":0,"k":[278.5,212,0],"ix":1},"s":{"a":0,"k":[100,100,100],"ix":6}},"ao":0,"ef":[{"ty":25,"nm":"Drop Shadow","np":8,"mn":"ADBE Drop Shadow","ix":1,"en":1,"ef":[{"ty":2,"nm":"Shadow Color","mn":"ADBE Drop Shadow-0001","ix":1,"v":{"a":0,"k":[0,0,0,1],"ix":1}},{"ty":0,"nm":"Opacity","mn":"ADBE Drop Shadow-0002","ix":2,"v":{"a":0,"k":127.5,"ix":2}},{"ty":0,"nm":"Direction","mn":"ADBE Drop Shadow-0003","ix":3,"v":{"a":0,"k":135,"ix":3}},{"ty":0,"nm":"Distance","mn":"ADBE Drop Shadow-0004","ix":4,"v":{"a":0,"k":5,"ix":4}},{"ty":0,"nm":"Softness","mn":"ADBE Drop Shadow-0005","ix":5,"v":{"a":0,"k":33,"ix":5}},{"ty":7,"nm":"Shadow Only","mn":"ADBE Drop Shadow-0006","ix":6,"v":{"a":0,"k":0,"ix":6}}]}],"w":557,"h":424,"ip":0,"op":240,"st":0,"bm":0},{"ddd":0,"ind":3,"ty":4,"nm":"Layer 4 Outlines 2","sr":1,"ks":{"o":{"a":0,"k":100,"ix":11},"r":{"a":0,"k":0,"ix":10},"p":{"a":0,"k":[352.484,267.931,0],"ix":2},"a":{"a":0,"k":[352.484,267.931,0],"ix":1},"s":{"a":0,"k":[100,100,100],"ix":6}},"ao":0,"shapes":[{"ty":"gr","it":[{"ind":0,"ty":"sh","ix":1,"ks":{"a":0,"k":{"i":[[0,0],[0.485,-0.063],[3.17,-2.272],[3.429,-4.042],[2.187,-3.925],[0.428,-4.48],[-1.999,-3.762],[-3.053,-1.761],[-0.144,-0.048],[-4.63,-0.049],[-1.21,0.159],[-3.96,3.564],[-1.713,5.66],[0.157,6.179],[0.26,1.181],[4.056,3.78],[3.232,0.101]],"o":[[-0.489,0.004],[-3.856,0.58],[-4.367,3.007],[-2.991,3.353],[-2.109,3.976],[-0.472,4.233],[1.69,3.229],[0.15,0.006],[4.141,2.069],[1.22,-0.002],[5.293,-0.599],[4.508,-4.09],[1.807,-5.981],[-0.541,-1.13],[-1.154,-5.269],[-2.255,-2.318],[0,0]],"v":[[9.833,-30.715],[8.37,-30.615],[-2.32,-26.276],[-14.065,-15.655],[-21.854,-4.705],[-25.697,8.104],[-23.355,20.375],[-15.854,27.415],[-15.411,27.495],[-2.082,30.715],[1.565,30.474],[15.792,24.074],[24.179,8.885],[26.012,-9.415],[25.426,-12.976],[18.39,-26.945],[9.835,-30.715]],"c":false},"ix":2},"nm":"Path 1","mn":"ADBE Vector Shape - Group","hd":false},{"ty":"fl","c":{"a":0,"k":[0.795999983245,0.905999995213,0.898000021542,1],"ix":4},"o":{"a":0,"k":100,"ix":5},"r":1,"bm":0,"nm":"Fill 1","mn":"ADBE Vector Graphic - Fill","hd":false},{"ty":"tr","p":{"a":0,"k":[397.101,448.876],"ix":2},"a":{"a":0,"k":[0,0],"ix":1},"s":{"a":1,"k":[{"i":{"x":[0.667,0.667],"y":[1,1]},"o":{"x":[0.333,0.333],"y":[0,0]},"t":160,"s":[100,100]},{"i":{"x":[0.667,0.667],"y":[1,1]},"o":{"x":[0.333,0.333],"y":[0,0]},"t":280,"s":[94,94]},{"t":399,"s":[100,100]}],"ix":3},"r":{"a":0,"k":0,"ix":6},"o":{"a":0,"k":100,"ix":7},"sk":{"a":1,"k":[{"i":{"x":[0.667],"y":[1]},"o":{"x":[0.333],"y":[0]},"t":160,"s":[0]},{"i":{"x":[0.667],"y":[1]},"o":{"x":[0.333],"y":[0]},"t":280,"s":[25]},{"t":399,"s":[0]}],"ix":4},"sa":{"a":1,"k":[{"i":{"x":[0.667],"y":[1]},"o":{"x":[0.333],"y":[0]},"t":160,"s":[0]},{"i":{"x":[0.667],"y":[1]},"o":{"x":[0.333],"y":[0]},"t":280,"s":[-48]},{"t":399,"s":[0]}],"ix":5},"nm":"Transform"}],"nm":"Group 1","np":4,"cix":2,"bm":0,"ix":1,"mn":"ADBE Vector Group","hd":false}],"ip":160,"op":400,"st":160,"bm":0},{"ddd":0,"ind":4,"ty":4,"nm":"Layer 4 Outlines","sr":1,"ks":{"o":{"a":0,"k":100,"ix":11},"r":{"a":0,"k":0,"ix":10},"p":{"a":0,"k":[352.484,267.931,0],"ix":2},"a":{"a":0,"k":[352.484,267.931,0],"ix":1},"s":{"a":0,"k":[100,100,100],"ix":6}},"ao":0,"shapes":[{"ty":"gr","it":[{"ind":0,"ty":"sh","ix":1,"ks":{"a":0,"k":{"i":[[0,0],[0.485,-0.063],[3.17,-2.272],[3.429,-4.042],[2.187,-3.925],[0.428,-4.48],[-1.999,-3.762],[-3.053,-1.761],[-0.144,-0.048],[-4.63,-0.049],[-1.21,0.159],[-3.96,3.564],[-1.713,5.66],[0.157,6.179],[0.26,1.181],[4.056,3.78],[3.232,0.101]],"o":[[-0.489,0.004],[-3.856,0.58],[-4.367,3.007],[-2.991,3.353],[-2.109,3.976],[-0.472,4.233],[1.69,3.229],[0.15,0.006],[4.141,2.069],[1.22,-0.002],[5.293,-0.599],[4.508,-4.09],[1.807,-5.981],[-0.541,-1.13],[-1.154,-5.269],[-2.255,-2.318],[0,0]],"v":[[9.833,-30.715],[8.37,-30.615],[-2.32,-26.276],[-14.065,-15.655],[-21.854,-4.705],[-25.697,8.104],[-23.355,20.375],[-15.854,27.415],[-15.411,27.495],[-2.082,30.715],[1.565,30.474],[15.792,24.074],[24.179,8.885],[26.012,-9.415],[25.426,-12.976],[18.39,-26.945],[9.835,-30.715]],"c":false},"ix":2},"nm":"Path 1","mn":"ADBE Vector Shape - Group","hd":false},{"ty":"fl","c":{"a":0,"k":[0.795999983245,0.905999995213,0.898000021542,1],"ix":4},"o":{"a":0,"k":100,"ix":5},"r":1,"bm":0,"nm":"Fill 1","mn":"ADBE Vector Graphic - Fill","hd":false},{"ty":"tr","p":{"a":0,"k":[397.101,448.876],"ix":2},"a":{"a":0,"k":[0,0],"ix":1},"s":{"a":1,"k":[{"i":{"x":[0.667,0.667],"y":[1,1]},"o":{"x":[0.333,0.333],"y":[0,0]},"t":-80,"s":[100,100]},{"i":{"x":[0.667,0.667],"y":[1,1]},"o":{"x":[0.333,0.333],"y":[0,0]},"t":40,"s":[94,94]},{"t":159,"s":[100,100]}],"ix":3},"r":{"a":0,"k":0,"ix":6},"o":{"a":0,"k":100,"ix":7},"sk":{"a":1,"k":[{"i":{"x":[0.667],"y":[1]},"o":{"x":[0.333],"y":[0]},"t":-80,"s":[0]},{"i":{"x":[0.667],"y":[1]},"o":{"x":[0.333],"y":[0]},"t":40,"s":[25]},{"t":159,"s":[0]}],"ix":4},"sa":{"a":1,"k":[{"i":{"x":[0.667],"y":[1]},"o":{"x":[0.333],"y":[0]},"t":-80,"s":[0]},{"i":{"x":[0.667],"y":[1]},"o":{"x":[0.333],"y":[0]},"t":40,"s":[-48]},{"t":159,"s":[0]}],"ix":5},"nm":"Transform"}],"nm":"Group 1","np":4,"cix":2,"bm":0,"ix":1,"mn":"ADBE Vector Group","hd":false}],"ip":-80,"op":160,"st":-80,"bm":0},{"ddd":0,"ind":5,"ty":4,"nm":"Layer 3 Outlines 2","sr":1,"ks":{"o":{"a":0,"k":100,"ix":11},"r":{"a":0,"k":0,"ix":10},"p":{"a":0,"k":[352.484,267.931,0],"ix":2},"a":{"a":0,"k":[352.484,267.931,0],"ix":1},"s":{"a":0,"k":[100,100,100],"ix":6}},"ao":0,"shapes":[{"ty":"gr","it":[{"ind":0,"ty":"sh","ix":1,"ks":{"a":0,"k":{"i":[[0,0],[-3.512,0.378],[-9.226,3.715],[-12.072,13.49],[5.1,16.12],[8.08,6.4],[1.977,0.89],[5.756,0.288],[5.971,-1.467],[19.346,-17.88],[1.98,-4.816],[-5.404,-11.46],[-1.842,-3.81],[-1.939,-1.54],[-9.264,-0.345]],"o":[[3.527,0.178],[9.887,-1.076],[16.517,-6.53],[11.183,-12.49],[-3.063,-9.69],[-1.943,-0.97],[-5.251,-2.375],[-6.143,-0.274],[-25.469,5.91],[-3.814,3.545],[-5.11,12.24],[1.813,3.839],[1.87,1.63],[7.267,5.756],[0,0]],"v":[[-26.345,54.978],[-15.77,54.678],[13.036,47.458],[57.298,19.538],[66.698,-23.432],[50.598,-47.962],[44.763,-50.852],[28.106,-54.882],[9.842,-53.082],[-57.894,-18.192],[-66.688,-5.502],[-63.899,29.868],[-57.407,40.718],[-51.787,45.588],[-26.342,54.978]],"c":false},"ix":2},"nm":"Path 1","mn":"ADBE Vector Shape - Group","hd":false},{"ty":"fl","c":{"a":0,"k":[0.795999983245,0.905999995213,0.898000021542,1],"ix":4},"o":{"a":0,"k":100,"ix":5},"r":1,"bm":0,"nm":"Fill 1","mn":"ADBE Vector Graphic - Fill","hd":false},{"ty":"tr","p":{"a":0,"k":[143.506,146.903],"ix":2},"a":{"a":0,"k":[0,0],"ix":1},"s":{"a":1,"k":[{"i":{"x":[0.667,0.667],"y":[1,1]},"o":{"x":[0.333,0.333],"y":[0,0]},"t":69,"s":[100,100]},{"i":{"x":[0.667,0.667],"y":[1,1]},"o":{"x":[0.333,0.333],"y":[0,0]},"t":189,"s":[94,94]},{"t":308,"s":[100,100]}],"ix":3},"r":{"a":0,"k":0,"ix":6},"o":{"a":0,"k":100,"ix":7},"sk":{"a":1,"k":[{"i":{"x":[0.667],"y":[1]},"o":{"x":[0.333],"y":[0]},"t":69,"s":[0]},{"i":{"x":[0.667],"y":[1]},"o":{"x":[0.333],"y":[0]},"t":189,"s":[25]},{"t":308,"s":[0]}],"ix":4},"sa":{"a":1,"k":[{"i":{"x":[0.667],"y":[1]},"o":{"x":[0.333],"y":[0]},"t":69,"s":[0]},{"i":{"x":[0.667],"y":[1]},"o":{"x":[0.333],"y":[0]},"t":189,"s":[-48]},{"t":308,"s":[0]}],"ix":5},"nm":"Transform"}],"nm":"Group 1","np":4,"cix":2,"bm":0,"ix":1,"mn":"ADBE Vector Group","hd":false}],"ip":69,"op":309,"st":69,"bm":0},{"ddd":0,"ind":6,"ty":4,"nm":"Layer 3 Outlines","sr":1,"ks":{"o":{"a":0,"k":100,"ix":11},"r":{"a":0,"k":0,"ix":10},"p":{"a":0,"k":[352.484,267.931,0],"ix":2},"a":{"a":0,"k":[352.484,267.931,0],"ix":1},"s":{"a":0,"k":[100,100,100],"ix":6}},"ao":0,"shapes":[{"ty":"gr","it":[{"ind":0,"ty":"sh","ix":1,"ks":{"a":0,"k":{"i":[[0,0],[-3.512,0.378],[-9.226,3.715],[-12.072,13.49],[5.1,16.12],[8.08,6.4],[1.977,0.89],[5.756,0.288],[5.971,-1.467],[19.346,-17.88],[1.98,-4.816],[-5.404,-11.46],[-1.842,-3.81],[-1.939,-1.54],[-9.264,-0.345]],"o":[[3.527,0.178],[9.887,-1.076],[16.517,-6.53],[11.183,-12.49],[-3.063,-9.69],[-1.943,-0.97],[-5.251,-2.375],[-6.143,-0.274],[-25.469,5.91],[-3.814,3.545],[-5.11,12.24],[1.813,3.839],[1.87,1.63],[7.267,5.756],[0,0]],"v":[[-26.345,54.978],[-15.77,54.678],[13.036,47.458],[57.298,19.538],[66.698,-23.432],[50.598,-47.962],[44.763,-50.852],[28.106,-54.882],[9.842,-53.082],[-57.894,-18.192],[-66.688,-5.502],[-63.899,29.868],[-57.407,40.718],[-51.787,45.588],[-26.342,54.978]],"c":false},"ix":2},"nm":"Path 1","mn":"ADBE Vector Shape - Group","hd":false},{"ty":"fl","c":{"a":0,"k":[0.795999983245,0.905999995213,0.898000021542,1],"ix":4},"o":{"a":0,"k":100,"ix":5},"r":1,"bm":0,"nm":"Fill 1","mn":"ADBE Vector Graphic - Fill","hd":false},{"ty":"tr","p":{"a":0,"k":[143.506,146.903],"ix":2},"a":{"a":0,"k":[0,0],"ix":1},"s":{"a":1,"k":[{"i":{"x":[0.667,0.667],"y":[1,1]},"o":{"x":[0.333,0.333],"y":[0,0]},"t":-171,"s":[100,100]},{"i":{"x":[0.667,0.667],"y":[1,1]},"o":{"x":[0.333,0.333],"y":[0,0]},"t":-51,"s":[94,94]},{"t":68,"s":[100,100]}],"ix":3},"r":{"a":0,"k":0,"ix":6},"o":{"a":0,"k":100,"ix":7},"sk":{"a":1,"k":[{"i":{"x":[0.667],"y":[1]},"o":{"x":[0.333],"y":[0]},"t":-171,"s":[0]},{"i":{"x":[0.667],"y":[1]},"o":{"x":[0.333],"y":[0]},"t":-51,"s":[25]},{"t":68,"s":[0]}],"ix":4},"sa":{"a":1,"k":[{"i":{"x":[0.667],"y":[1]},"o":{"x":[0.333],"y":[0]},"t":-171,"s":[0]},{"i":{"x":[0.667],"y":[1]},"o":{"x":[0.333],"y":[0]},"t":-51,"s":[-48]},{"t":68,"s":[0]}],"ix":5},"nm":"Transform"}],"nm":"Group 1","np":4,"cix":2,"bm":0,"ix":1,"mn":"ADBE Vector Group","hd":false}],"ip":-171,"op":69,"st":-171,"bm":0},{"ddd":0,"ind":7,"ty":4,"nm":"Layer 2 Outlines","sr":1,"ks":{"o":{"a":0,"k":100,"ix":11},"r":{"a":0,"k":0,"ix":10},"p":{"a":0,"k":[352.484,267.931,0],"ix":2},"a":{"a":0,"k":[352.484,267.931,0],"ix":1},"s":{"a":0,"k":[100,100,100],"ix":6}},"ao":0,"shapes":[{"ty":"gr","it":[{"ind":0,"ty":"sh","ix":1,"ks":{"a":0,"k":{"i":[[0,0],[0.04,0],[48.105,-5.85],[3.435,-0.16],[22.859,4.7],[23.403,-1.05],[1.656,-0.13],[-28.239,-84.23],[-13.373,0.59],[-9.903,5.6],[-9.963,0.45],[-1.278,-0.128],[-0.063,-13.28],[9.06,-13.34],[-28.666,1.28],[-0.335,0.03],[-34.501,1.54],[-3.202,-0.292],[-53.375,2.39],[-11.739,4.465],[7.422,69.1],[-3.112,18.68],[-13.96,41.13],[49.954,-2.23]],"o":[[-0.04,0],[-49.029,2.25],[-3.458,0.42],[-23.337,1.04],[-22.858,-4.7],[-1.651,0.07],[-115.333,9.26],[6.073,18.11],[10.4,-0.47],[8.729,-4.93],[1.284,-0.061],[15.739,1.58],[0.08,16.46],[-38.558,56.77],[0.336,-0.02],[34.913,-2.17],[3.212,-0.146],[39.472,3.64],[12.54,-0.684],[47.557,-17.431],[-5.213,-48.52],[7.724,-46.37],[15.341,-45.22],[0,0]],"v":[[198.41,-208.64],[198.294,-208.63],[61.65,-167.71],[51.308,-166.85],[-17.725,-175.22],[-86.858,-183.58],[-91.818,-183.28],[-254.162,43.14],[-222.708,66.54],[-191.189,56.09],[-163.308,44.92],[-159.46,45.02],[-135.036,75.76],[-155.389,120.56],[-121.94,195.5],[-120.94,195.44],[-21.717,166.16],[-12.083,166.38],[109.998,208.48],[146.634,200.71],[219.922,69.37],[203.301,-13.29],[267.06,-129.14],[198.414,-208.64]],"c":false},"ix":2},"nm":"Path 1","mn":"ADBE Vector Shape - Group","hd":false},{"ty":"fl","c":{"a":0,"k":[0.936999990426,0.961000031116,0.969000004787,1],"ix":4},"o":{"a":0,"k":100,"ix":5},"r":1,"bm":0,"nm":"Fill 1","mn":"ADBE Vector Graphic - Fill","hd":false},{"ty":"tr","p":{"a":0,"k":[360.162,265.001],"ix":2},"a":{"a":0,"k":[0,0],"ix":1},"s":{"a":1,"k":[{"i":{"x":[0.667,0.667],"y":[1,1]},"o":{"x":[0.333,0.333],"y":[0,0]},"t":0,"s":[100,100]},{"i":{"x":[0.667,0.667],"y":[1,1]},"o":{"x":[0.333,0.333],"y":[0,0]},"t":120,"s":[94,94]},{"t":239,"s":[100,100]}],"ix":3},"r":{"a":0,"k":0,"ix":6},"o":{"a":0,"k":100,"ix":7},"sk":{"a":1,"k":[{"i":{"x":[0.667],"y":[1]},"o":{"x":[0.333],"y":[0]},"t":0,"s":[0]},{"i":{"x":[0.667],"y":[1]},"o":{"x":[0.333],"y":[0]},"t":120,"s":[-7]},{"t":239,"s":[0]}],"ix":4},"sa":{"a":1,"k":[{"i":{"x":[0.667],"y":[1]},"o":{"x":[0.333],"y":[0]},"t":0,"s":[0]},{"i":{"x":[0.667],"y":[1]},"o":{"x":[0.333],"y":[0]},"t":120,"s":[-48]},{"t":239,"s":[0]}],"ix":5},"nm":"Transform"}],"nm":"Group 1","np":4,"cix":2,"bm":0,"ix":1,"mn":"ADBE Vector Group","hd":false}],"ip":0,"op":240,"st":0,"bm":0}],"markers":[]}